{
    "commands": [
        {
            "name": "news",
            "description": "отключить/включить рассылку. В беседах доступно только администраторам",
            "prefixes": ["news"],
            "arguments": [
                "group - новости в группе (изначально включено / в лс выключено)",
                "— osuupdate - обновления osu! (изначально выключено)",
                "— newranked - новые ранкнутые карты (изначально выключено)",
                "— osunews - новости на сайте osu! (изначально включено / в лс выключено)"
            ]
        },
        {
            "name": "help",
            "description": "ссылка на помощь",
            "prefixes": ["help"],
            "arguments": []
        },
        {
            "name": "streams",
            "description": "топ-3 osu! стримера на Twitch по зрителям",
            "prefixes": ["streams"],
            "arguments": []
        },
        {
            "name": "status",
            "description": "Статус бота",
            "prefixes": ["status"],
            "arguments": []
        },
        {
            "name": "topcmds",
            "description": "топ команд по количеству использований",
            "prefixes": ["topcmds"],
            "arguments": []
        },
        {
            "name": "uptime",
            "description": "время работы бота",
            "prefixes": ["uptime"],
            "arguments": []
        },
        {
            "name": "search",
            "description": "поиск карт",
            "prefixes": ["uptime"],
            "arguments": [
                "запрос - слова по которым искать карту"
            ]
        },
        {
            "name": "nick",
            "description": "привязать ник к аккаунту ВК, чтобы не указывать его каждый раз в других командах",
            "prefixes": ["nick", "n"],
            "arguments": [
                "nickname - ник который вы хотите привязать"
            ]
        },
        {
            "name": "mode",
            "description": "установить режим игры",
            "prefixes": ["mode", "m"],
            "arguments": [
                "mode - цифра режима (0 — osu!, 1 — osu!taiko, 2 — osu!catch, 3 — osu!mania)"
            ]
        },
        {
            "name": "user",
            "description": "посмотреть статистику игрока",
            "prefixes": ["user", "u"],
            "arguments": [
                "nickname - необязательный параметр, чтобы посмотреть данные определенного игрока. Если не указан, то показывает статистику привязанного аккаунта"
            ]
        },
        {
            "name": "recent",
            "description": "посмотреть последний плей игрока",
            "prefixes": ["recent", "r"],
            "arguments": [
                "nickname - необязательный параметр. Посмотреть данные определенного игрока. Если не указан, то показывает статистику привязанного аккаунта",
                "\\n - необязательный параметр. Позволяет указать \"шаг назад\" для команды, чтобы посмотреть предыдущие данные. Если не указан, то показывает последние данные"
            ]
        },
        {
            "name": "top",
            "description": "показывает топ-3 скора игрока",
            "prefixes": ["top", "t"],
            "arguments": [
                "nickname - необязательный параметр. Посмотреть данные определенного игрока. Если не указан, то показывает статистику привязанного аккаунта",
                "~nnn — необязательнйы параметр. Показывает топ скор игрока, ближайший к nnn пп",
                ">nnn — необязательнйы параметр. Показывает сколько у игрока топ скоров больше nnn пп"
            ]
        },
        {
            "name": "compare",
            "description": "посмотреть лучший скор игрока на карте",
            "prefixes": ["compare", "c"],
            "arguments": [
                "nickname - необязательный параметр. Посмотреть данные определенного игрока. Если не указан, то показывает статистику привязанного аккаунта",
                "+mods - необязательный параметр. Позволяет получить данные с указанными модами (например, +HDDT)"
            ]
        },
        {
            "name": "chat",
            "description": "посмотреть топ беседы (ограничение на топ-15)",
            "prefixes": ["chat"],
            "arguments": [
                "ID - необязательный параметр. ID беседы, чтобы посмотреть полный топ беседы, напишите в ЛС боту s chat [ID]"
            ]
        },
        {
            "name": "find",
            "description": "найти пользователей в ВК по привязанному нику на данном сервере",
            "prefixes": ["find", "f"],
            "arguments": [
                "ID - необязательный параметр. ID беседы, чтобы посмотреть полный топ беседы, напишите в ЛС боту s chat [ID]"
            ]
        },
        {
            "name": "leaderboard",
            "description": "посмотреть топ беседы на карте",
            "prefixes": ["leaderboard", "lb"],
            "arguments": [
                "+mods - необязательный параметр. Позволяет получить данные с указанными модами (например, +HDDT)"
            ]
        }
    ]
}